nitwit/__init__.py
nitwit/cache.py
nitwit/py.typed
nitwit/references.py
nitwit/sources.py
nitwit/github/__init__.py
nitwit/github/github_cache.py
nitwit/github/github_collect.py
nitwit/github/github_endpoints.py
nitwit/github/github_getters.py
nitwit/github/github_requests.py
nitwit/tables/__init__.py
nitwit/tables/authors.py
nitwit/tables/commits.py
nitwit/tables/file_diffs.py
nitwit-0.1.1.dist-info/LICENSE-APACHE
nitwit-0.1.1.dist-info/LICENSE-MIT
nitwit-0.1.1.dist-info/WHEEL
nitwit-0.1.1.dist-info/METADATA
nitwit-0.1.1.dist-info/RECORD
