Metadata-Version: 2.1
Name: nitwit
Version: 0.1.1
Summary: tools for converting git repository data into data tables
Requires-Python: >=3.7
Classifier: Development Status :: 4 - Beta
Classifier: Intended Audience :: Developers
Classifier: Intended Audience :: Financial and Insurance Industry
Classifier: Intended Audience :: Science/Research
Classifier: License :: OSI Approved :: Apache Software License
Classifier: License :: OSI Approved :: MIT License
Classifier: Natural Language :: English
Classifier: Operating System :: MacOS
Classifier: Operating System :: Microsoft :: Windows
Classifier: Operating System :: POSIX :: Linux
Classifier: Programming Language :: Python :: 3.7
Classifier: Programming Language :: Python :: 3.8
Classifier: Programming Language :: Python :: 3.9
Classifier: Programming Language :: Python :: 3.10
Classifier: Programming Language :: Python :: 3.11
Classifier: Programming Language :: Python :: 3.12
Classifier: Typing :: Typed
Requires-Dist: polars >= 1.0
Requires-Dist: aiofiles >= 24.1.0
Requires-Dist: aiolimiter >= 1.2.1
Requires-Dist: aiohttp >= 3.9.5
Requires-Dist: typing-extensions >=4.9.0 ; extra == "test"
Project-URL: Documentation, https://github.com/paradigmxyz/nitwit
Project-URL: Source, https://github.com/paradigmxyz/nitwit
Provides-Extra: test
